studygovernor/__init__.py
studygovernor/__main__.py
studygovernor/control.py
studygovernor/exceptions.py
studygovernor/fields.py
studygovernor/models.py
studygovernor/views.py
studygovernor/api/__init__.py
studygovernor/api/health.py
studygovernor/api/v1/__init__.py
studygovernor/api/v1/action.py
studygovernor/api/v1/base.py
studygovernor/api/v1/callback.py
studygovernor/api/v1/cohort.py
studygovernor/api/v1/experiment.py
studygovernor/api/v1/external_objects.py
studygovernor/api/v1/role.py
studygovernor/api/v1/scan.py
studygovernor/api/v1/service.py
studygovernor/api/v1/state.py
studygovernor/api/v1/subject.py
studygovernor/api/v1/transition.py
studygovernor/api/v1/user.py
studygovernor/api/v1/workflow.py
studygovernor/api/v2/__init__.py
studygovernor/api/v2/action.py
studygovernor/api/v2/base.py
studygovernor/api/v2/callback.py
studygovernor/api/v2/cohort.py
studygovernor/api/v2/config.py
studygovernor/api/v2/experiment.py
studygovernor/api/v2/external_objects.py
studygovernor/api/v2/role.py
studygovernor/api/v2/scan.py
studygovernor/api/v2/service.py
studygovernor/api/v2/state.py
studygovernor/api/v2/subject.py
studygovernor/api/v2/summary_models.py
studygovernor/api/v2/transition.py
studygovernor/api/v2/user.py
studygovernor/api/v2/workflow.py
studygovernor/auth/__init__.py
studygovernor/auth/forms.py
studygovernor/auth/models.py
studygovernor/callbacks/__init__.py
studygovernor/callbacks/command.py
studygovernor/callbacks/create_task.py
studygovernor/callbacks/create_taskgroup.py
studygovernor/callbacks/docker_run.py
studygovernor/callbacks/external_program.py
studygovernor/callbacks/fastr.py
studygovernor/callbacks/python_function.py
studygovernor/callbacks/send_mail.py
studygovernor/callbacks/sleep.py
studygovernor/callbacks/backends/__init__.py
studygovernor/callbacks/backends/celery_backend.py
studygovernor/callbacks/backends/celery_worker.py
studygovernor/callbacks/backends/local_backend.py
studygovernor/callbacks/castor/__init__.py
studygovernor-8.1.0.dist-info/LICENSE
studygovernor-8.1.0.dist-info/METADATA
studygovernor-8.1.0.dist-info/WHEEL
studygovernor-8.1.0.dist-info/entry_points.txt
studygovernor-8.1.0.dist-info/top_level.txt
studygovernor-8.1.0.dist-info/RECORD
